CHANGELOG.md
LICENSE
README.md
loguru_configurable/__init__.py
loguru_configurable/_version.py
loguru_configurable/config.py
loguru_configurable/py.typed
loguru_configurable-0.2.0.dist-info/LICENSE
loguru_configurable-0.2.0.dist-info/METADATA
loguru_configurable-0.2.0.dist-info/WHEEL
loguru_configurable-0.2.0.dist-info/RECORD
