Metadata-Version: 2.1
Name: loguru_configurable
Version: 0.2.0
Summary: Wrapper that adds an application_settings ConfigSection to loguru
Home-page: https://github.com/StockwatchDev/loguru_configurable
License: MIT
Keywords: loguru,logging,configuration,application_settings,dataclass,pydantic,toml
Author: Stockwatchdevs
Author-email: stockwatchdevs@gmail.com
Requires-Python: >=3.10,<4.0
Classifier: Development Status :: 4 - Beta
Classifier: Intended Audience :: Developers
Classifier: License :: OSI Approved :: MIT License
Classifier: Natural Language :: English
Classifier: Operating System :: OS Independent
Classifier: Programming Language :: Python :: 3
Classifier: Programming Language :: Python :: 3.10
Classifier: Programming Language :: Python :: 3.11
Classifier: Programming Language :: Python :: 3.12
Classifier: Programming Language :: Python :: 3.13
Classifier: Topic :: Software Development :: Libraries :: Python Modules
Classifier: Typing :: Typed
Requires-Dist: application-settings (>=0.5)
Requires-Dist: loguru (>=0.7)
Requires-Dist: loguru-config (>=0.1)
Requires-Dist: loguru-logging-intercept (>=0.1)
Project-URL: Repository, https://github.com/StockwatchDev/loguru_configurable
